ciatta/__init__.py
ciatta/ciatta.py
ciatta/files.py
ciatta/fit.py
ciatta/plot.py
ciatta-1.1.4.dist-info/LICENSE
ciatta-1.1.4.dist-info/METADATA
ciatta-1.1.4.dist-info/WHEEL
ciatta-1.1.4.dist-info/RECORD
