Metadata-Version: 2.1
Name: ciatta
Version: 1.1.4
Summary: Analyzes CSV files for stress and strain
License: MIT
Author: Paride Azzari
Author-email: paride21azzari@gmail.com
Requires-Python: >=3.10,<3.13
Classifier: License :: OSI Approved :: MIT License
Classifier: Programming Language :: Python :: 3
Classifier: Programming Language :: Python :: 3.10
Classifier: Programming Language :: Python :: 3.11
Requires-Dist: colorama (>=0.4.4,<0.5.0)
Requires-Dist: fsspec (>=2023.9.1,<2024.0.0)
Requires-Dist: matplotlib (>=3.8.0,<4.0.0)
Requires-Dist: numpy (>=1.26.0,<2.0.0)
Requires-Dist: pandas (>=2.1.1,<3.0.0)
Requires-Dist: scipy (>=1.12.0,<2.0.0)
